get_papers/__init__.py
get_papers/fetch_papers.py
get_papers/utils.py
aganitha_intern_task-0.1.0.dist-info/METADATA
aganitha_intern_task-0.1.0.dist-info/WHEEL
aganitha_intern_task-0.1.0.dist-info/top_level.txt
aganitha_intern_task-0.1.0.dist-info/RECORD
