Metadata-Version: 2.1
Name: aganitha-intern-task
Version: 0.1.0
Author: VIGHNESH M S
Author-email: VIGHNESH M S <princevighnesh71@gmail.com>
Requires-Python: >=3.12
Requires-Dist: requests <3.0.0,>=2.32.3
Requires-Dist: pandas <3.0.0,>=2.2.3
